{
    "backup_directory": "D:\\backup",
    "home_directory": "C:\\Users",
    "source_directories": [
        "%HOME%\\Documents",
        "C:\\Path\\To\\Other\\Directory",
        "E:\\Path\\To\\Directory\\In\\Another\\Drive"
    ],
	"exclude_directories": [
		"%HOME%\\Documents\\do-not-backup"
	],
	"exclude_files": [],
    "source_files": [
        "%HOME%\\.gitconfig"
    ],
    "rotation": {
        "enabled": false,
        "interval": 30,
        "max_saved": 5
    },
    "debug": true,
    "dryrun": true,
    "notification": false
}
